jiraclient/__init__.py
jiraclient/jiraclient.py
jiraclient/version.py
jiraclient/worklogs.py
jiraclient-2.1.13.data/scripts/jiraclient
jiraclient-2.1.13.dist-info/METADATA
jiraclient-2.1.13.dist-info/WHEEL
jiraclient-2.1.13.dist-info/top_level.txt
jiraclient-2.1.13.dist-info/RECORD
