Metadata-Version: 2.1
Name: jiraclient
Version: 2.1.13
Summary: A REST client for Atlassian JIRA
Home-page: https://github.com/mcallaway/jiraclient
Author: Matthew Callaway
Author-email: UNKNOWN
License: GPL
Platform: UNKNOWN
Requires-Dist: restkit
Requires-Dist: PyYAML
